[
    {
        "_id": "6646e9ea64fe169a33396db2",
        "titulo": "Dune",
        "editora": "Companhia de Bolso",
        "preco": 12,
        "paginas": 123,
        "autor": {
            "nome": "Frank Herbert",
            "nacionalidade": "americano",
            "_id": "6646e8d364fe169a33396da9"
        }
    },
    {
        "_id": "6646ea4864fe169a33396db6",
        "titulo": "Dune Messiah",
        "editora": "Companhia de Bolso",
        "preco": 14,
        "paginas": 211,
        "autor": {
            "nome": "Frank Herbert",
            "nacionalidade": "americano",
            "_id": "6646e8d364fe169a33396da9"
        }
    },
    {
        "_id": "6646ec9064fe169a33396dc0",
        "titulo": "Sapiens",
        "editora": "LPM",
        "preco": 44,
        "paginas": 442,
        "autor": {
            "nome": "Yuval Noah Harari",
            "nacionalidade": "Israelense",
            "_id": "6646e8f264fe169a33396dab"
        }
    },
    {
        "_id": "6646ed5964fe169a33396dc6",
        "titulo": "Assim falou zaratustra",
        "editora": "Niilista",
        "preco": 24,
        "paginas": 101,
        "autor": {
            "nome": "Friedrich Nietzsche",
            "nacionalidade": "Alemão",
            "_id": "6646e92e64fe169a33396dae"
        }
    }
]